LICENSE
README.md
setup.py
py_error_boundary/__init__.py
py_error_boundary/error_boundary.py
py_error_boundary.egg-info/PKG-INFO
py_error_boundary.egg-info/SOURCES.txt
py_error_boundary.egg-info/dependency_links.txt
py_error_boundary.egg-info/top_level.txt