Metadata-Version: 2.1
Name: py-error-boundary
Version: 0.1.0
Summary: A simple Python package for explicit errors
Home-page: https://github.com/suyogkulkarnigit/py_error_boundary
Author: Suyog Kulkarni
Classifier: Programming Language :: Python :: 3
Classifier: Operating System :: OS Independent
Requires-Python: >=3.11
License-File: LICENSE
